README.rst
setup.py
ghform/__init__.py
ghform/cli.py
ghform/config.py
ghform/form.py
ghform/github.py
github_pr_form.egg-info/PKG-INFO
github_pr_form.egg-info/SOURCES.txt
github_pr_form.egg-info/dependency_links.txt
github_pr_form.egg-info/entry_points.txt
github_pr_form.egg-info/requires.txt
github_pr_form.egg-info/top_level.txt