Metadata-Version: 1.1
Name: github-pr-form
Version: 0.1.1
Summary: A small python utility for generating forms from the command line and adding them to GitHub pull requests or issues, while tracking them in a secondary github repo.
Home-page: https://github.com/aaron0browne/github-pr-form
Author: Aaron N Browne
Author-email: aaron0browne@gmail.com
License: MIT License
Download-URL: httpd://github.com/aaron0browne/github-pr-form/tarball/v0.1.1
Keywords: github,rfc,change control,form,pull request
Platform: UNKNOWN
Classifier: Development Status :: 4 - Beta
Classifier: Environment :: Console
Classifier: Intended Audience :: Developers
Classifier: License :: OSI Approved :: MIT License
Classifier: Natural Language :: English
Classifier: Programming Language :: Python
Classifier: Topic :: Software Development :: Version Control
